special_heatmap/__init__.py
special_heatmap/heatmap.py
special_heatmap-0.2.0.dist-info/METADATA
special_heatmap-0.2.0.dist-info/WHEEL
special_heatmap-0.2.0.dist-info/licenses/LICENSE
special_heatmap-0.2.0.dist-info/RECORD
