Metadata-Version: 2.4
Name: special-heatmap
Version: 0.2.0
Summary: A Python reproduction of the MATLAB Special Heatmap project.
Project-URL: Homepage, https://github.com/The-D66/python-special-heatmap
Project-URL: Repository, https://github.com/The-D66/python-special-heatmap
Project-URL: Issues, https://github.com/The-D66/python-special-heatmap/issues
Author-email: "The.D" <the-d@live.com>
License: GNU GENERAL PUBLIC LICENSE
License-File: LICENSE
Requires-Python: >=3.10
Requires-Dist: matplotlib>=3.10.8
Requires-Dist: numpy>=2.2.6
